instru/__init__.py
instru/adam6018.py
instru/adam6024.py
instru/bb60c.py
instru/bk4065.py
instru/demo.py
instru/ks33510b.py
instru/ksn9010b.py
instru/sds1102x.py
instru/ssm32q.py
instru/vmmd4.py
instru/webswitch.py
instru/x410.py
instru-0.1.29.dist-info/entry_points.txt
instru-0.1.29.dist-info/WHEEL
instru-0.1.29.dist-info/METADATA
instru-0.1.29.dist-info/RECORD
