Metadata-Version: 2.1
Name: instru
Version: 0.1.29
Summary: Various commonly used instrument drivers
Author: James Maxwell
Requires-Python: >=3.8,<4.0
Classifier: Programming Language :: Python :: 3
Classifier: Programming Language :: Python :: 3.8
Classifier: Programming Language :: Python :: 3.9
Requires-Dist: pymodbus (>=2.4.0,<3.0.0)
Requires-Dist: pyvisa-py (>=0.5.1,<0.6.0)
Requires-Dist: qcodes (>=0.22.0,<0.23.0)
